ndjsonlib/__init__.py
ndjsonlib/data_file.py
ndjsonlib/dataset_name.py
ndjsonlib/json_data_file.py
ndjsonlib/metadata_file.py
ndjsonlib/ndjson_data_file.py
ndjsonlib/models/__init__.py
ndjsonlib/models/dataset.py
ndjsonlib-0.0.4.dist-info/licenses/LICENSE.md
ndjsonlib-0.0.4.dist-info/METADATA
ndjsonlib-0.0.4.dist-info/WHEEL
ndjsonlib-0.0.4.dist-info/top_level.txt
ndjsonlib-0.0.4.dist-info/RECORD
