Metadata-Version: 2.4
Name: ndjsonlib
Version: 0.0.4
Summary: Read and write Dataset-JSON as NDJSON
Home-page: https://github.com/swhume/ndjsonlib
Author: Sam Hume
Author-email: swhume@gmail.com
License: MIT
License-File: LICENSE.md
Requires-Dist: pydantic~=2.11.3
Requires-Dist: ijson~=3.3.0
Dynamic: author
Dynamic: author-email
Dynamic: description
Dynamic: description-content-type
Dynamic: home-page
Dynamic: license
Dynamic: license-file
Dynamic: requires-dist
Dynamic: summary
